beanprice/__init__.py
beanprice/date_utils.py
beanprice/date_utils_test.py
beanprice/net_utils.py
beanprice/net_utils_test.py
beanprice/price.py
beanprice/price_test.py
beanprice/source.py
beanprice/sources/__init__.py
beanprice/sources/alphavantage.py
beanprice/sources/alphavantage_test.py
beanprice/sources/coinbase.py
beanprice/sources/coinbase_test.py
beanprice/sources/coincap.py
beanprice/sources/coincap_test.py
beanprice/sources/coinmarketcap.py
beanprice/sources/coinmarketcap_test.py
beanprice/sources/eastmoneyfund.py
beanprice/sources/eastmoneyfund_test.py
beanprice/sources/ecbrates.py
beanprice/sources/ecbrates_test.py
beanprice/sources/iex.py
beanprice/sources/iex_test.py
beanprice/sources/oanda.py
beanprice/sources/oanda_test.py
beanprice/sources/quandl.py
beanprice/sources/quandl_test.py
beanprice/sources/ratesapi.py
beanprice/sources/ratesapi_test.py
beanprice/sources/tsp.py
beanprice/sources/tsp_test.py
beanprice/sources/yahoo.py
beanprice/sources/yahoo_test.py
beanprice-2.1.0.dist-info/licenses/COPYING
experiments/dividends/download_dividends.py
beanprice-2.1.0.dist-info/METADATA
beanprice-2.1.0.dist-info/WHEEL
beanprice-2.1.0.dist-info/entry_points.txt
beanprice-2.1.0.dist-info/top_level.txt
beanprice-2.1.0.dist-info/RECORD
