Metadata-Version: 2.4
Name: beanprice
Version: 2.1.0
Summary: Price quotes fetcher for Beancount
Home-page: http://github.com/beancount/beanprice
Download-URL: https://github.com/beancount/beanprice
Author: Martin Blais
Author-email: Martin Blais <blais@furius.ca>
Maintainer-email: Martin Blais <blais@furius.ca>
Project-URL: homepage, https://github.com/beancount/beanprice
Project-URL: issues, https://github.com/beancount/beanprice/issues
Keywords: accounting,ledger,beancount,price
Classifier: License :: OSI Approved :: GNU General Public License v2 (GPLv2)
Classifier: Programming Language :: Python :: 3 :: Only
Classifier: Programming Language :: Python :: 3.9
Classifier: Programming Language :: Python :: 3.10
Classifier: Programming Language :: Python :: 3.11
Classifier: Programming Language :: Python :: 3.12
Classifier: Programming Language :: Python :: 3.13
Classifier: Programming Language :: SQL
Classifier: Topic :: Office/Business :: Financial :: Accounting
Requires-Python: >=3.9
License-File: COPYING
Requires-Dist: beancount>=3.0.0
Requires-Dist: python-dateutil>=2.6.0
Requires-Dist: requests>=2.0
Requires-Dist: curl_cffi>=0.6.5
Requires-Dist: diskcache>=5.6.3
Dynamic: author
Dynamic: download-url
Dynamic: home-page
Dynamic: license-file
Dynamic: requires-python
